mentalpoker/__init__.py
mentalpoker/dealer.py
mentalpoker/elgamal.py
mentalpoker/elliptic.py
mentalpoker/utils.py
mentalpoker-0.5.0.dist-info/LICENSE
mentalpoker-0.5.0.dist-info/METADATA
mentalpoker-0.5.0.dist-info/WHEEL
mentalpoker-0.5.0.dist-info/top_level.txt
mentalpoker-0.5.0.dist-info/RECORD
